odoo10_addon_product_brand-10.0.1.0.0-py2.7-nspkg.pth
odoo10_addon_product_brand-10.0.1.0.0.dist-info/top_level.txt
odoo10_addon_product_brand-10.0.1.0.0.dist-info/WHEEL
odoo10_addon_product_brand-10.0.1.0.0.dist-info/RECORD
odoo10_addon_product_brand-10.0.1.0.0.dist-info/metadata.json
odoo10_addon_product_brand-10.0.1.0.0.dist-info/DESCRIPTION.rst
odoo10_addon_product_brand-10.0.1.0.0.dist-info/METADATA
odoo10_addon_product_brand-10.0.1.0.0.dist-info/namespace_packages.txt
odoo/addons/product_brand/__manifest__.py
odoo/addons/product_brand/__init__.py
odoo/addons/product_brand/README.rst
odoo/addons/product_brand/security/ir.model.access.csv
odoo/addons/product_brand/models/product_brand.py
odoo/addons/product_brand/models/__init__.py
odoo/addons/product_brand/i18n/fr_FR.po
odoo/addons/product_brand/i18n/product_brand.pot
odoo/addons/product_brand/i18n/fr.po
odoo/addons/product_brand/views/product_brand_view.xml
odoo/addons/product_brand/static/description/icon.png
