Metadata-Version: 2.0
Name: odoo10-addon-product-brand
Version: 10.0.1.0.0
Summary: Product Brand Manager
Home-page: UNKNOWN
Author: NetAndCo, Akretion, Prisnet Telecommunications SA, MONK Software, Odoo Community Association (OCA), SerpentCS Pvt. Ltd.
Author-email: support@odoo-community.org
License: AGPL-3
Platform: UNKNOWN
Requires-Dist: odoo (<10.1dev,>=10.0)
Classifier: Programming Language :: Python :: 2.7
Classifier: Framework :: Odoo
Classifier: License :: OSI Approved :: GNU Affero General Public License v3
